Workbook
Name customer: Revenue!$B$4:$D$4
Name location1: 'P&L'!$B$1
Name location2: 'P&L'!$C$1
Name location3: 'P&L'!$D$1
Name Price: Revenue!$B$5:$D$5
Name Revenuepermonth: Revenue!$B$6:$D$6
Name Revenuepermonthaftercalculations: Revenue!$B$13
Name Revenueperyear: Revenue!$B$7:$D$7
Name Revenueperyearaftercalculations: Revenue!$B$14:$D$14

Sheet P&L
A1: Location | B1: New Bustand | C1: Palay Market | D1: Near Jose School
A2: Mode of Ownership | B2: Rental | C2: Rental | D2: Rental
B3: Year 1 | C3: Year 1 | D3: Year 1 | H3: Rental / Fixed Costs | I3: =20000*12 -> 240000 | J3: =15000*12 -> 180000 | K3: =10000*12 -> 120000
A4: Revenue | B4: {=Revenueperyear} -> 719520 | C4: 834504 | D4: 1349100 | H4: OPEX | I4: New Bus Stand | J4: Palay Market | K4: Near Jose School
A5: Total Staff Cost | B5: =Cost!B39 -> 384000 | C5: =Cost!C39 -> 768000 | D5: =Cost!D39 -> 960000 | H5: rent | I5: =I3 -> 240000 | J5: =J3 -> 180000 | K5: =K3 -> 120000
A6: Capital Investment | B6: =Capital!$B$11 -> 270000 | C6: =Capital!$C$11 -> 265000 | D6: =Capital!$D$11 -> 260000 | H6: marketing | I6: ='Expenses Newbustand'!B48 -> 13500 | J6: ='Expenses Newbustand'!C48 -> 18000 | K6: ='Expenses Newbustand'!D48 -> 13500
A7: Gross Profit | B7: =$B$4-$B$5 -> 335520 | C7: =$C$4-$C$5 -> 66504 | D7: =$D$4-$D$5 -> 389100 | H7: Tot | I7: =$I$5+$I$6 -> 253500 | J7: =$J$5+$J$6 -> 198000 | K7: =$K$5+$K$6 -> 133500
A8: Operating Profit | B8: =$B$7-$I$7 -> 82020 | C8: =$C$7-$J$7 -> -131496 | D8: =$D$7-$K$7 -> 255600
A9: ROI | B9: =($B$8/$B$6)*100 -> 30.377778 | C9: =$C$8/$C$6*100 -> -49.621132 | D9: =$D$8/$D$6*100 -> 98.307692 | H9: ROI | I9: =I15/B6 -> 0.35377778 | J9: =J15/C6 -> -0.42828679 | K9: =K15/D6 -> 1.035
A10: Payback Period | B10: =$B$6/$B$8 -> 3.29188 | C10: NO Payback | D10: =$D$6/$D$8 -> 1.0172144
H11: Pay Back Period in Yrs ( If Loan) | I11: =B6/I15 -> 2.8266332 | J11: =C6/J15 -> -2.334884 | K11: =D6/K15 -> 0.96618357
H13: Profitability for Part time | I13: =B4-I18-I3 -> 287520 | J13: =C4-J18-J3 -> 270504 | K13: =D4-K18-K3 -> 749100
A14: Location | B14: New Bustand | C14: Palay Market | D14: Near Jose School | H14: Profitability for Full time | I14: =B4-I19-I3 -> 287520 | J14: =C4-J19-J3 -> 270504 | K14: =D4-K19-K3 -> 749100
A15: Mode of Ownership | B15: Rental | C15: Rental | D15: Rental | H15: Profitability For Total Staff | I15: =B4-B5-I3 -> 95520 | J15: =C4-C5-J3 -> -113496 | K15: =D4-D5-K3 -> 269100
B16: Year 1 | C16: Year 1 | D16: Year 1
A17: Revenue | B17: {=Revenueperyear} -> 719520 | C17: 834504 | D17: 1349100 | H17: Cost
A18: Gross Profit | B18: =$B$4-$B$5 -> 335520 | C18: =$C$4-$C$5 -> 66504 | D18: =$D$4-$D$5 -> 389100 | H18: Cost of operations Part time | I18: =Cost!B37 -> 192000 | J18: =Cost!C37 -> 384000 | K18: =Cost!D37 -> 480000
A19: Total Operating Expenses | B19: =$I$5+$I$6 -> 253500 | C19: =$J$5+$J$6 -> 198000 | D19: =$K$5+$K$6 -> 133500 | H19: Cost of operations Full time | I19: =Cost!B38 -> 192000 | J19: =Cost!C38 -> 384000 | K19: =Cost!D38 -> 480000
A20: Operating Profit | B20: =$B$7-$I$7 -> 82020 | C20: =$C$7-$J$7 -> -131496 | D20: =$D$7-$K$7 -> 255600
A21: Capital Investment | B21: =Capital!$B$11 -> 270000 | C21: =Capital!$C$11 -> 265000 | D21: =Capital!$D$11 -> 260000
A22: ROI | B22: =($B$8/$B$6)*100 -> 30.377778 | C22: =$C$8/$C$6*100 -> -49.621132 | D22: =$D$8/$D$6*100 -> 98.307692
A23: Payback Period | B23: =$B$6/$B$8 -> 3.29188 | C23: NO Payback | D23: =$D$6/$D$8 -> 1.0172144

Sheet Pricing and Average Spending
B1: Jan | C1: Feb | D1: Mar | E1: Apr | F1: May | G1: Jun | H1: July | I1: Aug | J1: Sep | K1: Oct | L1: Nov | M1: Dec | O1: Year 1 | P1: Year 2 | Q1: Year 3
A3: Price Model for New Bustand | B3: 1250 | C3: 1499 | D3: 1499 | E3: 1499 | F3: 1499 | G3: 1499 | H3: 1499 | I3: 1499 | J3: 1250 | K3: 1499 | L3: 1499 | M3: 1499 | P3: 1599 | Q3: 1650
A4: Price Model for Palay Market | B4: 1099 | C4: 1200 | D4: 1200 | E4: 1200 | F4: 1200 | G4: 1200 | H4: 1200 | I4: 1200 | J4: 1200 | K4: 1200 | L4: 1200 | M4: 1200 | P4: 1299 | Q4: 1350
A5: Price Model Near Jose School | B5: 1250 | C5: 1499 | D5: 1499 | E5: 1499 | F5: 1499 | G5: 1499 | H5: 1499 | I5: 1499 | J5: 1250 | K5: 1499 | L5: 1499 | M5: 1499 | P5: 1599 | Q5: 1650
A8: Revenue Per month New Bustand | B8: =B3*31 -> 38750 | C8: =C3*28 -> 41972 | D8: =D3*31 -> 46469 | E8: =E3*30 -> 44970 | F8: =F3*31 -> 46469 | G8: =G3*30 -> 44970 | H8: =H3*31 -> 46469 | I8: =I3*31 -> 46469 | J8: =J3*30 -> 37500 | K8: =K3*31 -> 46469 | L8: =L3*30 -> 44970 | M8: =M3*31 -> 46469 | O8: =SUM(B8:M8) -> 531946 | P8: =P3*365 -> 583635 | Q8: =Q3*365 -> 602250
A9: Revenue Per month Palay Market | B9: =B4*31 -> 34069 | C9: =C4*28 -> 33600 | D9: =D4*31 -> 37200 | E9: =E4*30 -> 36000 | F9: =F4*31 -> 37200 | G9: =G4*30 -> 36000 | H9: =H4*31 -> 37200 | I9: =I4*30 -> 36000 | J9: =J4*30 -> 36000 | K9: =K4*31 -> 37200 | L9: =L4*30 -> 36000 | M9: =M4*31 -> 37200 | O9: =SUM(B9:M9) -> 433669 | P9: =P4*365 -> 474135 | Q9: =Q4*365 -> 492750
A10: Revenue Per month Jose School | B10: =B5*31 -> 38750 | C10: =C5*28 -> 41972 | D10: =D5*31 -> 46469 | E10: =E5*30 -> 44970 | F10: =F5*31 -> 46469 | G10: =G5*30 -> 44970 | H10: =H5*31 -> 46469 | I10: =I5*31 -> 46469 | J10: =J5*30 -> 37500 | K10: =K5*31 -> 46469 | L10: =L5*30 -> 44970 | M10: =M5*31 -> 46469 | O10: =SUM(B10:M10) -> 531946 | P10: =P5*365 -> 583635 | Q10: =Q5*365 -> 602250

Sheet Customer Acquisition
A1: Month | B1: Factor | C1: Jan | D1: Feb | E1: Mar | F1: Apr | G1: May | H1: Jun | I1: July | J1: Aug | K1: Sep | L1: Oct | M1: Nov | N1: Dec
A3: Revenue
A4: Residents Newbusstand | C4: 500 | D4: 500 | E4: 500 | F4: 500 | G4: 500 | H4: 500 | I4: 500 | J4: 500 | K4: 500 | L4: 500 | M4: 500 | N4: 500
A5: Residents Palay Market | C5: 650 | D5: 650 | E5: 650 | F5: 650 | G5: 650 | H5: 650 | I5: 650 | J5: 650 | K5: 650 | L5: 650 | M5: 650 | N5: 650
A6: Residents Jose school | C6: 600 | D6: 600 | E6: 600 | F6: 600 | G6: 600 | H6: 600 | I6: 600 | J6: 600 | K6: 600 | L6: 600 | M6: 600 | N6: 600
A8: Admissions Newbustand | C8: 40 | D8: 40 | E8: 40 | F8: 40 | G8: 40 | H8: 40 | I8: 40 | J8: 40 | K8: 40 | L8: 40 | M8: 40 | N8: 40
A9: Admissions Palay Market | C9: 58 | D9: 58 | E9: 58 | F9: 58 | G9: 58 | H9: 58 | I9: 58 | J9: 58 | K9: 58 | L9: 58 | M9: 58 | N9: 58
A10: Admissions Jose school | C10: 75 | D10: 75 | E10: 75 | F10: 75 | G10: 75 | H10: 75 | I10: 75 | J10: 75 | K10: 75 | L10: 75 | M10: 75 | N10: 75
A11: Increase in Admissions Monthly | B11: 2
A13: Total available Market Newbustand | C13: 50
A14: Total available Market Palay Market | C14: 75
A15: Total available Market Jose School | C15: 150
C16: Over all of the 3 markets
A17: Target Audience (Chemistry Weak Students) | C17: 875
A18: Total Addressable Market | C18: 175
A20: Current Captured | C20: 700
A23: Target Market to Capture | C23: 290
A24: No of Estimated Admission per month | C24: 6

Sheet Expenses Newbustand
B1: ='Customer Acquisition'!C1 -> Jan | C1: ='Customer Acquisition'!D1 -> Feb | D1: ='Customer Acquisition'!E1 -> Mar | E1: ='Customer Acquisition'!F1 -> Apr | F1: ='Customer Acquisition'!G1 -> May | G1: ='Customer Acquisition'!H1 -> Jun | H1: ='Customer Acquisition'!I1 -> July | I1: ='Customer Acquisition'!J1 -> Aug | ... M1: ='Customer Acquisition'!N1 -> Dec | O1: Yr 1 | P1: Yr 2 | Q1: Yr 3
A2: Customers Newbustand | B2: ='Customer Acquisition'!C8 -> 40 | C2: ='Customer Acquisition'!D8 -> 40 | D2: ='Customer Acquisition'!E8 -> 40 | E2: ='Customer Acquisition'!F8 -> 40 | F2: ='Customer Acquisition'!G8 -> 40 | G2: ='Customer Acquisition'!H8 -> 40 | H2: ='Customer Acquisition'!I8 -> 40 | I2: ='Customer Acquisition'!J8 -> 40 | ... M2: ='Customer Acquisition'!N8 -> 40 | O2: 40
A3: Cost of Sales for Newbustand | B3: =$B$19*B2 -> 59960 | C3: =$B$19*C2 -> 59960 | D3: =$B$19*D2 -> 59960 | E3: =$B$19*E2 -> 59960 | F3: =$B$19*F2 -> 59960 | G3: =$B$19*G2 -> 59960 | H3: =$B$19*H2 -> 59960 | I3: =$B$19*I2 -> 59960 | ... M3: =$B$19*M2 -> 59960 | O3: =O2*1499 -> 59960
A4: Labour Cost for Newbustand | B4: =$F$28 -> 32000 | C4: =$F$28 -> 32000 | D4: =$F$28 -> 32000 | E4: =$F$28 -> 32000 | F4: =$F$28 -> 32000 | G4: =$F$28 -> 32000 | H4: =$F$28 -> 32000 | I4: =$F$28 -> 32000 | ... M4: =$F$28 -> 32000 | O4: =SUM(B4:M4) -> 384000
A5: Operating Cost | B5: 15000 | J5: 15000
A6: Misc | B6: 5000 | C6: 5000 | D6: 5000 | E6: 5000 | F6: 5000 | G6: 5000 | H6: 5000 | I6: 5000 | J6: 5000 | K6: 5000 | L6: 5000 | M6: 5000
B7: =SUM(B3:B6) -> 111960 | C7: =SUM(C3:C6) -> 96960 | D7: =SUM(D3:D6) -> 96960 | E7: =SUM(E3:E6) -> 96960 | F7: =SUM(F3:F6) -> 96960 | G7: =SUM(G3:G6) -> 96960 | H7: =SUM(H3:H6) -> 96960 | I7: =SUM(I3:I6) -> 96960 | ... M7: =SUM(M3:M6) -> 96960
A9: Operating Cost
A10: Furniture | B10: =Cost!B28 -> 21500
A11: Marketing | B11: =Cost!B27 -> 15000 | J11: =Cost!B27 -> 15000
B12: =B10+B11 -> 36500
A18: Cost of Sale Per Admission Per month
A19: Newbustand | B19: 1499
A20: Palay Market | B20: 1199
A21: Jose School | B21: 1499
A25: Cost of Labour
A26: Labour | B26: Newbustand | C26: Palay Market | D26: Joseschool | F26: New bustand | G26: Palay Market | H26: Joseschool
A27: No of Students | B27: 40 | C27: 58 | D27: 75
A28: Total Staff | B28: 6 | C28: 9 | D28: 12 | F28: =F29+F30 -> 32000 | G28: =G29+G30 -> 48000 | H28: =H29+H30 -> 64000
A29: Part time staff | B29: 4 | C29: 6 | D29: 8 | F29: =B29*B33 -> 16000 | G29: =C29*C33 -> 24000 | H29: =D29*D33 -> 32000
A30: Full time Staff | B30: 2 | C30: 3 | D30: 4 | F30: =B30*B34 -> 16000 | G30: =C30*C34 -> 24000 | H30: =D30*D34 -> 32000
A32: Cost Per person
A33: part time per month | B33: 4000 | C33: 4000 | D33: 4000
A34: full time per month | B34: 8000 | C34: 8000 | D34: 8000
A36: Total Cost of Labour
A37: part time per year | B37: =B33*B29 -> 16000 | C37: =C33*C29 -> 24000 | D37: =D33*D29 -> 32000
A38: full time per year | B38: =B34*B30 -> 16000 | C38: =C34*C30 -> 24000 | D38: =D34*D30 -> 32000
A40: Total Staff Per Year | B40: =B38+B37 -> 32000 | C40: =C38+C37 -> 48000 | D40: =D38+D37 -> 64000
A43: Marketing | B43: New | C43: Palay
A44: Paperback | B44: 8000 | C44: 10000 | D44: 8000
A45: Distributing paperback | B45: 2000 | C45: 4000 | D45: 2000
A46: Digi | B46: 1500 | C46: 2000 | D46: 1500
A47: Influencer | B47: 2000 | C47: 2000 | D47: 2000
B48: =SUM(B44:B47) -> 13500 | C48: =SUM(C44:C47) -> 18000 | D48: =SUM(D44:D47) -> 13500

Sheet Expenses Palay Market
B1: ='Expenses Newbustand'!B1 -> Jan | C1: ='Expenses Newbustand'!C1 -> Feb | D1: ='Expenses Newbustand'!D1 -> Mar | E1: ='Expenses Newbustand'!E1 -> Apr | F1: ='Expenses Newbustand'!F1 -> May | G1: ='Expenses Newbustand'!G1 -> Jun | H1: ='Expenses Newbustand'!H1 -> July | I1: ='Expenses Newbustand'!I1 -> Aug | ... M1: ='Expenses Newbustand'!M1 -> Dec | O1: Yr 1 | P1: Yr 2 | Q1: Yr 3
A2: Customers Palay Market | B2: ='Customer Acquisition'!C9 -> 58 | C2: ='Customer Acquisition'!D9 -> 58 | D2: ='Customer Acquisition'!E9 -> 58 | E2: ='Customer Acquisition'!F9 -> 58 | F2: ='Customer Acquisition'!G9 -> 58 | G2: ='Customer Acquisition'!H9 -> 58 | H2: ='Customer Acquisition'!I9 -> 58 | I2: ='Customer Acquisition'!J9 -> 58 | ... M2: ='Customer Acquisition'!N9 -> 58 | O2: 58
A3: Cost of Sales for Palay Market | B3: =$B$16*B2 -> 69542 | C3: =$B$16*C2 -> 69542 | D3: =$B$16*D2 -> 69542 | E3: =$B$16*E2 -> 69542 | F3: =$B$16*F2 -> 69542 | G3: =$B$16*G2 -> 69542 | H3: =$B$16*H2 -> 69542 | I3: =$B$16*I2 -> 69542 | ... M3: =$B$16*M2 -> 69542 | O3: =58*1199 -> 69542
A4: Labour Cost for Palay market | B4: ='Expenses Newbustand'!$G$28 -> 48000 | C4: ='Expenses Newbustand'!$G$28 -> 48000 | D4: ='Expenses Newbustand'!$G$28 -> 48000 | E4: ='Expenses Newbustand'!$G$28 -> 48000 | F4: ='Expenses Newbustand'!$G$28 -> 48000 | G4: ='Expenses Newbustand'!$G$28 -> 48000 | H4: ='Expenses Newbustand'!$G$28 -> 48000 | I4: ='Expenses Newbustand'!$G$28 -> 48000 | ... M4: ='Expenses Newbustand'!$G$28 -> 48000 | O4: =SUM(B4:M4) -> 576000
A5: Operating Cost | B5: 20000 | J5: 20000
A6: Misc | B6: 5000 | C6: 5000 | D6: 5000 | E6: 5000 | F6: 5000 | G6: 5000 | H6: 5000 | I6: 5000 | J6: 5000 | K6: 5000 | L6: 5000 | M6: 5000
B7: =SUM(B3:B6) -> 142542 | C7: =SUM(C3:C6) -> 122542 | D7: =SUM(D3:D6) -> 122542 | E7: =SUM(E3:E6) -> 122542 | F7: =SUM(F3:F6) -> 122542 | G7: =SUM(G3:G6) -> 122542 | H7: =SUM(H3:H6) -> 122542 | I7: =SUM(I3:I6) -> 122542 | ... M7: =SUM(M3:M6) -> 122542
A14: Cost of Sale Per Admission Per month
A15: Newbustand | B15: 1499
A16: Palay Market | B16: 1199
A17: Jose School | B17: 1499

Sheet Expenses Jose School
B1: ='Customer Acquisition'!C1 -> Jan | C1: ='Customer Acquisition'!D1 -> Feb | D1: ='Customer Acquisition'!E1 -> Mar | E1: ='Customer Acquisition'!F1 -> Apr | F1: ='Customer Acquisition'!G1 -> May | G1: ='Customer Acquisition'!H1 -> Jun | H1: ='Customer Acquisition'!I1 -> July | I1: ='Customer Acquisition'!J1 -> Aug | ... M1: ='Customer Acquisition'!N1 -> Dec | O1: Yr 1 | P1: Yr 2 | Q1: Yr 3
A2: Customers Jose School | B2: ='Customer Acquisition'!C10 -> 75 | C2: ='Customer Acquisition'!D10 -> 75 | D2: ='Customer Acquisition'!E10 -> 75 | E2: ='Customer Acquisition'!F10 -> 75 | F2: ='Customer Acquisition'!G10 -> 75 | G2: ='Customer Acquisition'!H10 -> 75 | H2: ='Customer Acquisition'!I10 -> 75 | I2: ='Customer Acquisition'!J10 -> 75 | ... M2: ='Customer Acquisition'!N10 -> 75 | O2: 75
A3: Cost of Sales for Jose School | B3: =$B$16*B2 -> 112425 | C3: =$B$16*C2 -> 112425 | D3: =$B$16*D2 -> 112425 | E3: =$B$16*E2 -> 112425 | F3: =$B$16*F2 -> 112425 | G3: =$B$16*G2 -> 112425 | H3: =$B$16*H2 -> 112425 | I3: =$B$16*I2 -> 112425 | ... M3: =$B$16*M2 -> 112425 | O3: =75*1499 -> 112425
A4: Labour Cost for Jose School | B4: ='Expenses Newbustand'!$H$28 -> 64000 | C4: ='Expenses Newbustand'!$H$28 -> 64000 | D4: ='Expenses Newbustand'!$H$28 -> 64000 | E4: ='Expenses Newbustand'!$H$28 -> 64000 | F4: ='Expenses Newbustand'!$H$28 -> 64000 | G4: ='Expenses Newbustand'!$H$28 -> 64000 | H4: ='Expenses Newbustand'!$H$28 -> 64000 | I4: ='Expenses Newbustand'!$H$28 -> 64000 | ... M4: ='Expenses Newbustand'!$H$28 -> 64000 | O4: =SUM(B4:M4) -> 768000
A5: Operating cost | B5: 15000 | J5: 15000
A6: Misc | B6: 10000 | C6: 10000 | D6: 10000 | E6: 10000 | F6: 10000 | G6: 10000 | H6: 10000 | I6: 10000 | J6: 10000 | K6: 10000 | L6: 10000 | M6: 10000
B7: =SUM(B3:B6) -> 201425 | C7: =SUM(C3:C6) -> 186425 | D7: =SUM(D3:D6) -> 186425 | E7: =SUM(E3:E6) -> 186425 | F7: =SUM(F3:F6) -> 186425 | G7: =SUM(G3:G6) -> 186425 | H7: =SUM(H3:H6) -> 186425 | I7: =SUM(I3:I6) -> 186425 | ... M7: =SUM(M3:M6) -> 186425
A13: Cost of Sale Per Admission Per month
A14: Newbustand | B14: 1499
A15: Palay Market | B15: 1199
A16: Jose School | B16: 1499

Sheet Revenue
A1: Location | B1: =location1 -> New Bustand | C1: =location2 -> Palay Market | D1: =location3 -> Near Jose School | H1: This model uses structured inputs and supports monthly and quarterly forecasting for revenue planning | O1: Information Source is based on the Gemini and Assumption
A3: Revenue | G3: Average students strength in Near Jose School
A4: No. of . Customers | B4: 40 | C4: 58 | D4: 75 | G4: Jose school | H4: RoseMary Ram Nagar | I4: Pusphalatha
A5: Price | B5: 1499 | C5: 1199 | D5: 1499 | G5: 500 | H5: 500 | I5: 800
A6: Revenue Per Month | B6: {=customer*Price} -> 59960 | C6: 69542 | D6: 112425 | H6: Capturable MKT
A7: Revenue Per Year | B7: =B6*12 -> 719520 | C7: =C6*12 -> 834504 | D7: =D6*12 -> 1349100
A9: Price
A10: Revenue
A11: No. of . Customers | B11: 40 | C11: 58 | D11: 75
A12: Price | B12: 300 | C12: 250 | D12: 200
A13: Revenue Per Month | B13: =$B$11*$B$12 -> 12000 | C13: =$C$11*$C$12 -> 14500 | D13: =$D$11*$D$12 -> 15000 | F13: Avg | G13: =AVERAGE($G$5:$I$5) -> 600 | H13: =G13/1000 -> 0.6
A14: Revenue Per Year | B14: =B13*12 -> 144000 | C14: =C13*12 -> 174000 | D14: =D13*12 -> 180000
A17: Gross Profit
A22: Average students strength | B22: =location1 -> New Bustand | C22: =location2 -> Palay Market | D22: =location3 -> Near Jose School | G22: Average students strength in Palaymarket
A23: Resident Students avg & Total Available MKT | B23: =AVERAGE($G$30:$I$30) -> 500 | C23: =AVERAGE($G$24:$H$24:$I$24:$J$24) -> 650 | D23: =AVERAGE($G$5:$I$5) -> 600 | G23: Child Jesus | H23: St Johns | I23: Chrithu Raja | J23: ST Antonys | K23: RoseMary
G24: 600 | H24: 800 | I24: 600 | J24: 600 | K24: 500
A25: Target Audience, Chemistry weak students | B25: =B23/2 -> 250 | C25: =C23/2 -> 325 | D25: =D23/2 -> 300 | H25: Capturable MKT
B26: =B25/1000 -> 0.25 | C26: =C25/1000 -> 0.325 | D26: =D25/1000 -> 0.3 | F26: Avg | G26: =AVERAGE($G$24:$H$24:$I$24:$J$24) -> 650 | H26: =G26/1000 -> 0.65
A28: Current Captured MKT | B28: 200 | C28: 250 | D28: 150 | G28: Average students strength in Newbustand
A29: Target Capturable MKT by ( Blue Ocen Strategy) | B29: =B25-B28 -> 50 | C29: =C25-C28 -> 75 | D29: =D25-D28 -> 150 | G29: Vedic | H29: Al Madinah | I29: RoseMary
B30: =B29/B25 -> 0.2 | C30: =C29/C25 -> 0.23076923 | D30: =D29/D25 -> 0.5 | G30: 500 | H30: 500 | I30: 500
A31: No. of Estimated Admissions we can get | B31: =B28*B30 -> 40 | C31: =ROUNDUP(C28*C30,0) -> 58 | D31: =D28*D30 -> 75 | H31: Capturable MKT
F32: Avg | G32: =AVERAGE($G$30:$I$30) -> 500 | H32: =G32/1000 -> 0.5
A35: Price Model | B35: Chemistry | C35: .
A36: Based on MY Cost | B36: 500 | C36: 800 | D36: 1200
A37: Competition | B37: 800 | C37: 600 | D37: 1000
A38: Value Proposition
A39: My Decision | B39: 1500 | C39: 1200 | D39: 1500
A44: Cost of Sale | B44: Cost of 1 | C44: Cost of 1 | D44: Cost of 1 | E44: Number | F44: Number | G44: UOM ( Unit Of Measurement) | H44: Price | I44: UOM Price | J44: Conversion | K44: Cost | L44: Cost
A45: Notes ( A4) | E45: 5 | F45: 5 | G45: A4 | H45: 1 | I45: 20 Sheets | J45: =5/20 -> 0.25 | K45: =($E$45*$H$45*J46) -> 1.5 | L45: =(E45*H45*J45) -> 1.25
A46: Tests | E46: 5 | F46: 5 | G46: Ruled Paper | H46: 1.5 | I46: =1*5 -> 5 | J46: =1.5/5 -> 0.3 | K46: =($E$46*$H$46*$J$46) -> 2.25 | L46: =($E$46*$H$46*$J$46) -> 2.25
A47: Staff | E47: 1 | F47: 5 | G47: Staff | H47: 1 | I47: 6000 | J47: =1/6000 -> 0.00016666667 | K47: =(E47*H47*J47) -> 0.00016666667 | L47: =(F47*H47*J47) -> 0.00083333333

Sheet Capital
B1: =Revenue!B1 -> New Bustand | C1: =Revenue!C1 -> Palay Market | D1: =Revenue!D1 -> Near Jose School
A2: Customers | B2: =Revenue!B31 -> 40 | C2: =Revenue!C31 -> 58 | D2: =Revenue!D31 -> 75
A5: Capital requirements | B5: Rental | C5: Rental | D5: Rental
A6: Property Rent | B6: 20000 | C6: 15000 | D6: 10000
A7: Property Rent Advance | B7: 100000 | C7: 100000 | D7: 100000
A8: Interior/Partition | B8: 100000 | C8: 100000 | D8: 100000
A9: Furniture | B9: 50000 | C9: 50000 | D9: 50000
A11: Total Initial Investment | B11: =SUM(B6:B9) -> 270000 | C11: =SUM(C6:C9) -> 265000 | D11: =SUM(D6:D9) -> 260000

Sheet Cost
A1: Cost of Sale | B1: Cost of 1 | C1: Cost of 1 | D1: Cost of 1 | E1: Number | F1: Number | G1: UOM ( Unit Of Measurement) | H1: Price | I1: UOM Price | J1: Conversion | K1: Cost | L1: Cost
A2: Notes ( A4) | E2: 5 | F2: 5 | G2: A4 | H2: 1 | I2: 20 Sheets | J2: =5/20 -> 0.25 | K2: =($E$37*$H$37*$J$2) -> 0 | L2: =(E2*H2*J2) -> 1.25
A3: Tests | E3: 5 | F3: 5 | G3: Ruled Paper | H3: 1.5 | I3: =1*5 -> 5 | J3: =1.5/5 -> 0.3 | K3: =Cost!E3*Cost!H3*Cost!J3 -> 2.25 | L3: =E3*H3*J3 -> 2.25
A4: Staff | E4: 1 | F4: 5 | G4: Staff cost per test | H4: 1 | I4: 6000 | J4: =1/6000 -> 0.00016666667 | K4: =(E4*H4*J4) -> 0.00016666667 | L4: =(F4*H4*J4) -> 0.00083333333
A7: Staff Monthly salary | B7: working hrs per day | C7: Monthly working hours | E7: cost per hour | F7: Cost of teacher per student ( per month)
A8: 6000 | B8: 5.5 | C8: =B8*26 -> 143 | E8: =6000/143 -> 41.958042
A10: Test paper per student | B10: 1 test paper | C10: 8 tests per month | E10: Notes paper per student | F10: 1 notes paper | G10: 26 days
B11: 2.25 | C11: =8*B11 -> 18 | F11: 1.25 | G11: =F11*26 -> 32.5
A13: For Location 1 40 students | B13: per student share for a teacher salary | D13: For location 2 per student share for salary | G13: For location 3 per student share for staff
B14: =6000/40 -> 150 | D14: =6000/58 -> 103.44828 | G14: =6000/75 -> 80
A16: =location1 -> New Bustand | D16: =location2 -> Palay Market | G16: =location3 -> Near Jose School
A17: Test paper | B17: 18 | D17: Test paper | E17: 18 | G17: Test paper | H17: 18
A18: notes | B18: 32.5 | D18: notes | E18: 32.5 | G18: notes | H18: 32.5
A19: staff | B19: 150 | D19: staff | E19: =6000/58 -> 103.44828 | G19: staff | H19: =6000/75 -> 80
B20: =SUM(B17:B19) -> 200.5 | E20: =SUM(E17:E19) -> 153.94828 | H20: =SUM(H17:H19) -> 130.5
A21: Profit Margin | B21: =200*20/100 -> 40 | D21: Profit Margin | E21: =153.9483*20/100 -> 30.78966 | G21: Profit Margin | H21: =130*20/100 -> 26
A22: Total | B22: =SUM(B20,B21) -> 240.5 | D22: Total | E22: =SUM(E20,E21) -> 184.73794 | G22: Total | H22: =SUM(H20,H21) -> 156.5
A23: Rounded off | B23: 250 | D23: Rounded off | E23: 200 | G23: Rounded off | H23: 200
A26: Cost of operations per yr
A27: Marketing | B27: 15000 | E27: 20000 | H27: 15000
A28: Furniture | B28: 21500 | E28: 31000 | H28: 40000
A30: Labour cost per month
A31: =Labour!A12 -> part time per year | B31: =Labour!B12 -> 16000 | C31: =Labour!C12 -> 32000 | D31: =Labour!D12 -> 40000
A32: =Labour!A13 -> full time per year | B32: =Labour!B13 -> 16000 | C32: =Labour!C13 -> 32000 | D32: =Labour!D13 -> 40000
A33: =Labour!A15 -> Total Staff Per Year | B33: =Labour!B15 -> 32000 | C33: =Labour!C15 -> 64000 | D33: =Labour!D15 -> 80000
A36: Labour cost per yr
A37: =A31 -> part time per year | B37: =B31*12 -> 192000 | C37: =C31*12 -> 384000 | D37: =D31*12 -> 480000
A38: =A32 -> full time per year | B38: =B32*12 -> 192000 | C38: =C32*12 -> 384000 | D38: =D32*12 -> 480000
A39: =Labour!A15 -> Total Staff Per Year | B39: =B33*12 -> 384000 | C39: =C33*12 -> 768000 | D39: =D33*12 -> 960000

Sheet Labour
A1: Labour | B1: Newbustand | C1: Mall | D1: Joseschool
A2: No of Students | B2: 40 | C2: 58 | D2: 75
A3: Total Staff | B3: 6 | C3: =ROUNDUP(C2/5,0) -> 12 | D3: =D2/5 -> 15
A4: Part time staff | B4: 4 | C4: 8 | D4: 10
A5: Full time Staff | B5: 2 | C5: 4 | D5: 5
A7: Cost Per person
A8: part time per month | B8: 4000 | C8: 4000 | D8: 4000
A9: full time per month | B9: 8000 | C9: 8000 | D9: 8000
A11: Total Cost of Labour
A12: part time per year | B12: =B8*B4 -> 16000 | C12: =C8*C4 -> 32000 | D12: =D8*D4 -> 40000
A13: full time per year | B13: =B9*B5 -> 16000 | C13: =C9*C5 -> 32000 | D13: =D9*D5 -> 40000
A15: Total Staff Per Year | B15: =B13+B12 -> 32000 | C15: =C13+C12 -> 64000 | D15: =D13+D12 -> 80000

Sheet CapEx
B1: Jan | C1: Feb | D1: Mar | E1: Apr | F1: May | G1: Jun | H1: July | I1: Aug | J1: Sep | K1: Oct | L1: Nov | M1: Dec
A2: Total Number of Customers
A3: New | B3: 40 | C3: 40 | D3: 40 | E3: 40 | F3: 40 | G3: 40 | H3: 40 | I3: 40 | J3: 40 | K3: 40 | L3: 40 | M3: 40
A4: Palay | B4: 58 | C4: 58 | D4: 58 | E4: 58 | F4: 58 | G4: 58 | H4: 58 | I4: 58 | J4: 58 | K4: 58 | L4: 58 | M4: 58
A5: Jose | B5: 75 | C5: 75 | D5: 75 | E5: 75 | F5: 75 | G5: 75 | H5: 75 | I5: 75 | J5: 75 | K5: 75 | L5: 75 | M5: 75
A7: Furniture
A8: New | B8: =Cost!$B$28 -> 21500 | C8: =Cost!$B$28 -> 21500 | D8: =Cost!$B$28 -> 21500 | E8: =Cost!$B$28 -> 21500 | F8: =Cost!$B$28 -> 21500 | G8: =Cost!$B$28 -> 21500 | H8: =Cost!$B$28 -> 21500 | I8: =Cost!$B$28 -> 21500 | ... M8: =Cost!$B$28 -> 21500
A9: Palay | B9: =Cost!$E$28 -> 31000 | C9: =Cost!$E$28 -> 31000 | D9: =Cost!$E$28 -> 31000 | E9: =Cost!$E$28 -> 31000 | F9: =Cost!$E$28 -> 31000 | G9: =Cost!$E$28 -> 31000 | H9: =Cost!$E$28 -> 31000 | I9: =Cost!$E$28 -> 31000 | ... M9: =Cost!$E$28 -> 31000
A10: Jose | B10: =Cost!$H$28 -> 40000 | C10: =Cost!$H$28 -> 40000 | D10: =Cost!$H$28 -> 40000 | E10: =Cost!$H$28 -> 40000 | F10: =Cost!$H$28 -> 40000 | G10: =Cost!$H$28 -> 40000 | H10: =Cost!$H$28 -> 40000 | I10: =Cost!$H$28 -> 40000 | ... M10: =Cost!$H$28 -> 40000
A11: Decorations | B11: 5000
K12: 5000 | M12: 5000
